StreaMAX/__init__.py
StreaMAX/constants.py
StreaMAX/generator.py
StreaMAX/integrants.py
StreaMAX/methods.py
StreaMAX/potentials.py
StreaMAX/utils.py
streamax-0.3.1.dist-info/licenses/LICENSE
streamax-0.3.1.dist-info/METADATA
streamax-0.3.1.dist-info/WHEEL
streamax-0.3.1.dist-info/top_level.txt
streamax-0.3.1.dist-info/RECORD
