Metadata-Version: 2.4
Name: streamax
Version: 0.3.1
Summary: A JAX-accelerated stream generator (StreaMAX)
Home-page: https://github.com/David-Chemaly/StreaMAX
Author: David
Author-email: dc824@cam.ac.uk
Classifier: Programming Language :: Python :: 3
Classifier: License :: OSI Approved :: MIT License
Classifier: Operating System :: OS Independent
Requires-Python: >=3.7
License-File: LICENSE
Requires-Dist: jax>=0.4.0
Requires-Dist: astropy>=5.0.0
Dynamic: author
Dynamic: author-email
Dynamic: classifier
Dynamic: description
Dynamic: description-content-type
Dynamic: home-page
Dynamic: license-file
Dynamic: requires-dist
Dynamic: requires-python
Dynamic: summary
